{
    "DataType": "CustomerData",
    "DataVersion": 0,
    "GameVersion": "0.3.4f4",
    "Dependence": 0.9624999761581421,
    "PurchaseableProducts": [
        "bananacum",
        "icecreamshart"
    ],
    "ProductAffinities": [
        0.534375011920929,
        1.0,
        1.0
    ],
    "TimeSinceLastDealCompleted": 2503,
    "TimeSinceLastDealOffered": 1553,
    "OfferedDeals": 72,
    "CompletedDeals": 57,
    "IsContractOffered": false,
    "OfferedContract": {
        "Payment": 0.0,
        "Products": {
            "entries": []
        },
        "DeliveryLocationGUID": "",
        "DeliveryWindow": {
            "IsEnabled": false,
            "WindowStartTime": 1200,
            "WindowEndTime": 1800
        },
        "Expires": false,
        "ExpiresAfter": 0,
        "PickupScheduleIndex": 0,
        "IsCounterOffer": false
    },
    "OfferedContractTime": {
        "elapsedDays": 131,
        "time": 2230
    },
    "TimeSincePlayerApproached": 31431,
    "TimeSinceInstantDealOffered": 47718,
    "HasBeenRecommended": false
}